prysk/__init__.py
prysk/__main__.py
prysk/cli.py
prysk/diff.py
prysk/process.py
prysk/settings.py
prysk/test.py
prysk/xunit.py
prysk-0.20.0.dist-info/COPYING.txt
prysk-0.20.0.dist-info/METADATA
prysk-0.20.0.dist-info/WHEEL
prysk-0.20.0.dist-info/entry_points.txt
prysk-0.20.0.dist-info/RECORD
