Metadata-Version: 2.1
Name: prysk
Version: 0.20.0
Summary: Functional tests for command line applications
Home-page: https://www.prysk.net/
License: GNU GPLv2 or any later version
Keywords: test framework,snapshot testing,testing,cli,functional tests
Author: Nicola Coretti
Author-email: nico.coretti@gmail.com
Requires-Python: >=3.8,<4.0.0
Classifier: Development Status :: 5 - Production/Stable
Classifier: Environment :: Console
Classifier: Framework :: Pytest
Classifier: Intended Audience :: Developers
Classifier: License :: OSI Approved :: GNU General Public License (GPL)
Classifier: License :: OSI Approved :: GNU General Public License v2 or later (GPLv2+)
Classifier: License :: Other/Proprietary License
Classifier: Natural Language :: English
Classifier: Operating System :: OS Independent
Classifier: Programming Language :: Python :: 3
Classifier: Programming Language :: Python :: 3.8
Classifier: Programming Language :: Python :: 3.9
Classifier: Programming Language :: Python :: 3.10
Classifier: Programming Language :: Python :: 3.11
Classifier: Programming Language :: Python :: 3
Classifier: Programming Language :: Unix Shell
Classifier: Topic :: Software Development :: Testing
Provides-Extra: pytest-plugin
Requires-Dist: pytest-prysk (>=0.2.0,<0.3.0) ; extra == "pytest-plugin"
Requires-Dist: rich (>=13.3.1,<14.0.0)
Project-URL: Repository, https://github.com/prysk/prysk
